[
    {
        "course_id": "6358020b1279b6d3558d8fae",
        "title": "C plus plus Language",
        "thumbnail": "https://i.ibb.co/fxsbHSd/cpp.png",
        "authorImage": "https://i.ibb.co/r2hvDvH/two.jpg",
        "authorName": "Joann Knapp",
        "skills": [
            "html",
            "css",
            "bootstrap",
            "tailwind",
            "figma"
        ],
        "rating": 4.9,
        "reviews": 2000,
        "courseType": "Advance",
        "CourseDuration": "3 months"
    },
    {
        "course_id": "6358020b1279b6d3558d8f99",
        "title": "Dart Language",
        "thumbnail": "https://i.ibb.co/W6VtksD/dart.png",
        "authorImage": "https://i.ibb.co/gZpqVt8/tweenty.jpg",
        "authorName": "Joann Knapp",
        "skills": [
            "html",
            "css",
            "bootstrap",
            "tailwind",
            "figma"
        ],
        "rating": 4.9,
        "reviews": 2000,
        "courseType": "Advance",
        "CourseDuration": "3 months"
    },
    {
        "course_id": "6358020b1279b6d3558d8f00",
        "title": "Go Language",
        "thumbnail": "https://i.ibb.co/b6YFcmR/go.png",
        "authorImage": "https://i.ibb.co/vZDJWt5/six.jpg",
        "authorName": "Joann Knapp",
        "skills": [
            "html",
            "css",
            "bootstrap",
            "tailwind",
            "figma"
        ],
        "rating": 4.9,
        "reviews": 2000,
        "courseType": "Advance",
        "CourseDuration": "3 months"
    },
    {
        "course_id": "6358020b1279b6d3558d8f88",
        "title": "Java Language",
        "thumbnail": "https://i.ibb.co/7jsW0f6/java.png",
        "authorImage": "https://i.ibb.co/rFt09j6/seven.jpg",
        "authorName": "Joann Knapp",
        "skills": [
            "html",
            "css",
            "bootstrap",
            "tailwind",
            "figma"
        ],
        "rating": 4.9,
        "reviews": 2000,
        "courseType": "Advance",
        "CourseDuration": "3 months"
    },
    {
        "course_id": "6358020b1279b6d3558d8f22",
        "title": "Javascript Language",
        "thumbnail": "https://i.ibb.co/FWB1YQf/javascript.jpg",
        "authorImage": "https://i.ibb.co/Hg6GdG5/nineteen.jpg",
        "authorName": "Joann Knapp",
        "skills": [
            "html",
            "css",
            "bootstrap",
            "tailwind",
            "figma"
        ],
        "rating": 4.9,
        "reviews": 2000,
        "courseType": "Advance",
        "CourseDuration": "3 months"
    },
    {
        "course_id": "6358020b1279b6d3558d8f55",
        "title": "Python Language",
        "thumbnail": "https://i.ibb.co/h10FtVt/python.png",
        "authorImage": "https://i.ibb.co/wyCwv2k/nine.jpg",
        "authorName": "Joann Knapp",
        "skills": [
            "html",
            "css",
            "bootstrap",
            "tailwind",
            "figma"
        ],
        "rating": 4.9,
        "reviews": 2000,
        "courseType": "Advance",
        "CourseDuration": "3 months"
    }
]